[
  {
    "brand": "Tech Power",
    "date" : "10-10-20222",
    "status": false,
    "due": "2031.25",
    "more": "You Must Pay Now",
    "images" : "images/brand1.png"
  },
  {
    "brand": "Gwen Power",
    "date" : "10-12-20222",
    "status": false,
    "due": "100.25",
    "more": "You Must in two day",
    "images" : "images/brand2.png"

  },
  {
    "brand": "Air Power",
    "date" : "10-10-20222",
    "status": false,
    "due": "30000.25",
    "more": "You Must Pay after 2 weeks",
    "images" : "images/brand3.png"

  }
]